yamlargparse.py
yamlargparse_tests.py
yamlargparse-1.31.1.dist-info/METADATA
yamlargparse-1.31.1.dist-info/RECORD
yamlargparse-1.31.1.dist-info/WHEEL
yamlargparse-1.31.1.dist-info/top_level.txt
