Metadata-Version: 2.1
Name: yamlargparse
Version: 1.31.1
Summary: Parsing of command line options, yaml config files and/or environment variables based on argparse.
Home-page: https://omni-us.github.io/jsonargparse/
Author: Mauricio Villegas
Author-email: mauricio@omnius.com
License: MIT
Platform: UNKNOWN
Requires-Python: >=3.5
Requires-Dist: PyYAML (>=3.13)
